pygentree/__init__.py
pygentree/__main__.py
pygentree/tree_generator.py
pygentree-1.0.4.dist-info/LICENSE
pygentree-1.0.4.dist-info/METADATA
pygentree-1.0.4.dist-info/WHEEL
pygentree-1.0.4.dist-info/entry_points.txt
pygentree-1.0.4.dist-info/top_level.txt
pygentree-1.0.4.dist-info/RECORD
