Metadata-Version: 2.1
Name: pygentree
Version: 1.0.4
Summary: A Python package to generate ASCII tree representation of directory structures
Home-page: https://github.com/taeefnajib/pygentree
Author: Taeef Najib
Author-email: Taeef Najib <taeefnajib@gmail.com>
License: MIT License
Project-URL: Homepage, https://github.com/taeefnajib/pygentree
Keywords: directory,tree,filesystem,ascii
Classifier: License :: OSI Approved :: MIT License
Classifier: Programming Language :: Python
Classifier: Programming Language :: Python :: 3
Requires-Python: >=3.6
License-File: LICENSE
